tictactoetools/__init__.py
tictactoetools/tictac_exceptions.py
tictactoetools/tictactoetools.py
tictactoetools/data/tic_tac_toe.db
tictactoetools-2.1.1.dist-info/LICENSE
tictactoetools-2.1.1.dist-info/METADATA
tictactoetools-2.1.1.dist-info/WHEEL
tictactoetools-2.1.1.dist-info/top_level.txt
tictactoetools-2.1.1.dist-info/RECORD
