Metadata-Version: 2.1
Name: tictactoetools
Version: 2.1.1
Summary: Creatively build Tic-Tac-Toe matches and store their data in a database of all users.
Home-page: https://github.com/SimonValentino/tictactoetools.git
Author: Simon Valentino
Author-email: simontvalentino@gmail.com
License-File: LICENSE
Requires-Dist: mysql-connector-python (>=8.0.33)
